slash_step/__init__.py
slash_step/__version__.py
slash_step/_compat.py
slash_step/hooks.py
slash_step/step.py
slash_step-1.2.0.dist-info/METADATA
slash_step-1.2.0.dist-info/WHEEL
slash_step-1.2.0.dist-info/licenses/LICENSE
slash_step-1.2.0.dist-info/RECORD
