Metadata-Version: 2.3
Name: slash-step
Version: 1.2.0
Summary: A more granular sub STEP for slash tests
Project-URL: Homepage, https://github.com/getslash/slash-step
Author-email: Omer Gertel <omer.gertel@gmail.com>
License: BSD 3-Clause License
License-File: LICENSE
Classifier: Programming Language :: Python :: 3.8
Classifier: Programming Language :: Python :: 3.9
Classifier: Programming Language :: Python :: 3.10
Classifier: Programming Language :: Python :: 3.11
Classifier: Programming Language :: Python :: 3.12
Requires-Python: >=3.8
Requires-Dist: gossip
Requires-Dist: logbook>=1.2.0
Requires-Dist: slash>=0.7.0
Provides-Extra: testing
Requires-Dist: munch; extra == 'testing'
Requires-Dist: pylint; extra == 'testing'
Requires-Dist: pytest; extra == 'testing'
